yenta/__init__.py
yenta/cli.py
yenta/artifacts/Artifact.py
yenta/artifacts/__init__.py
yenta/config/__init__.py
yenta/config/logging.py
yenta/config/settings.py
yenta/pipeline/Pipeline.py
yenta/pipeline/__init__.py
yenta/tasks/Task.py
yenta/tasks/__init__.py
yenta/utils/__init__.py
yenta/utils/files.py
yenta-0.4.0.dist-info/AUTHORS.rst
yenta-0.4.0.dist-info/LICENSE
yenta-0.4.0.dist-info/METADATA
yenta-0.4.0.dist-info/WHEEL
yenta-0.4.0.dist-info/entry_points.txt
yenta-0.4.0.dist-info/top_level.txt
yenta-0.4.0.dist-info/RECORD
