Metadata-Version: 2.1
Name: yenta
Version: 0.4.0
Summary: Yet 'Nother Taskrunner
Home-page: https://github.com/grapesmoker/yenta
Author: Jerry Vinokurov
Author-email: grapesmoker@gmail.com
License: MIT license
Keywords: yenta
Platform: UNKNOWN
Classifier: Development Status :: 3 - Alpha
Classifier: Intended Audience :: Developers
Classifier: License :: OSI Approved :: MIT License
Classifier: Natural Language :: English
Classifier: Programming Language :: Python :: 3
Classifier: Programming Language :: Python :: 3.5
Classifier: Programming Language :: Python :: 3.6
Classifier: Programming Language :: Python :: 3.7
Classifier: Programming Language :: Python :: 3.8
Requires-Python: >=3.5
License-File: LICENSE
License-File: AUTHORS.rst
Requires-Dist: Click (>=7.0)
Requires-Dist: networkx (~=2.5)
Requires-Dist: colorama (~=0.4.3)
Requires-Dist: pydot (~=1.4.1)
Requires-Dist: rich (>=9.4.0)
Requires-Dist: more-itertools (~=8.7.0)
